picasso/__init__.py
picasso/nonthermal.py
picasso/polytrop.py
picasso/polytrop_ostriker.py
picasso/predictors.py
picasso/test_data.py
picasso/data/halos.hdf5
picasso/data/halos_576.npz
picasso/data/inputs_compact_576.npz
picasso/trained_models/576/Gamma_r.hdf5
picasso/trained_models/576/baseline.hdf5
picasso/trained_models/576/compact.hdf5
picasso/trained_models/576/compact_subgrid.hdf5
picasso/trained_models/576/minimal.hdf5
picasso/trained_models/576/nonradiative_Gamma_r.hdf5
picasso/trained_models/576/subgrid.hdf5
picasso/trained_models/576/subgrid_Gamma_r.hdf5
picasso/utils/__init__.py
picasso/utils/data_preparation.py
picasso/utils/hacc.py
picasso/utils/jax_utils.py
picasso/utils/plots.py
picasso_cosmo-1.1.4.dist-info/METADATA
picasso_cosmo-1.1.4.dist-info/WHEEL
picasso_cosmo-1.1.4.dist-info/licenses/LICENSE
picasso_cosmo-1.1.4.dist-info/RECORD
