Metadata-Version: 2.4
Name: picasso-cosmo
Version: 1.1.4
Summary: Painting intracluster gas on gravity-only simulations
Author-email: Florian Keruzore <florian.keruzore@gmail.com>
License-Expression: MIT
License-File: LICENSE
Requires-Python: >=3.10
Requires-Dist: h5py>=3.14.0
Requires-Dist: numpy>=2.2.6
Provides-Extra: jax
Requires-Dist: flax>=0.10.7; extra == 'jax'
Requires-Dist: jax>=0.6.2; extra == 'jax'
